LICENSE
MANIFEST.in
README.md
setup.cfg
setup.py
envy/__init__.py
envy/application.py
envy/decorators.py
envy.egg-info/PKG-INFO
envy.egg-info/SOURCES.txt
envy.egg-info/dependency_links.txt
envy.egg-info/entry_points.txt
envy.egg-info/pbr.json
envy.egg-info/requires.txt
envy.egg-info/top_level.txt
tests/#envy_test.py#
tests/__init__.py
tests/envy_acceptance_test.py
tests/envy_clean_all_test.py~
tests/envy_test.py
tests/envy_test_clean_all.py~
tests/testsrc/someuser/.virtualenvs/someenv/lib/python2.7/site-packages/some_package/base.py
tests/testsrc/someuser/src/some_package/setup.py
tests/testsrc/someuser/src/some_package/some_package/base.py
tests/testsrc/someuser/src/some_package/some_package/test.py